{"errors":[],"warnings":[],"namedChunkGroups":{"app":{"chunks":[6,4,0,2],"assets":["webpack-runtime-a0180772fb473043f032.js","webpack-runtime-a0180772fb473043f032.js.map","framework-9b7b0aa78083a4c4cab6.js","framework-9b7b0aa78083a4c4cab6.js.map","commons-c0f44b9b54d65fa911d5.js","commons-c0f44b9b54d65fa911d5.js.map","app-a9d83d7b8c5eafe652fe.js","app-a9d83d7b8c5eafe652fe.js.map"],"children":{},"childAssets":{}},"component---src-pages-index-js":{"chunks":[5,1,3,0],"assets":["styles.de76a92a80d32702478b.css","styles-9476d3c0c5a45461c039.js","styles-9476d3c0c5a45461c039.js.map","a9a7754c-0fc3a30fcccc5f337cca.js","a9a7754c-0fc3a30fcccc5f337cca.js.map","cb1608f2-693e64ef44b1eeb3672d.js","cb1608f2-693e64ef44b1eeb3672d.js.map","commons-c0f44b9b54d65fa911d5.js","commons-c0f44b9b54d65fa911d5.js.map"],"children":{},"childAssets":{}}},"assetsByChunkName":{"app":["webpack-runtime-a0180772fb473043f032.js","framework-9b7b0aa78083a4c4cab6.js","commons-c0f44b9b54d65fa911d5.js","app-a9d83d7b8c5eafe652fe.js"],"component---src-pages-index-js":["styles.de76a92a80d32702478b.css","styles-9476d3c0c5a45461c039.js","a9a7754c-0fc3a30fcccc5f337cca.js","cb1608f2-693e64ef44b1eeb3672d.js","commons-c0f44b9b54d65fa911d5.js"]}}